ElegantDevelopment/AWSCDKFeatureFlags/__init__.py
ElegantDevelopment/AWSCDKFeatureFlags/py.typed
ElegantDevelopment/AWSCDKFeatureFlags/_jsii/__init__.py
ElegantDevelopment/AWSCDKFeatureFlags/_jsii/aws-cdk-featureflags@0.1.2.jsii.tgz
aws_cdk_featureflags-0.1.2.dist-info/METADATA
aws_cdk_featureflags-0.1.2.dist-info/WHEEL
aws_cdk_featureflags-0.1.2.dist-info/top_level.txt
aws_cdk_featureflags-0.1.2.dist-info/RECORD
