Metadata-Version: 2.1
Name: aws-cdk-featureflags
Version: 0.1.2
Summary: An AWS CDK feature flag implementation
Home-page: https://github.com/elegantdevelopment/aws-cdk-featureflags#readme
Author: Justin Taylor<jtaylor@elegantdevelopment.co.uk>
License: Apache-2.0
Project-URL: Source, https://github.com/elegantdevelopment/aws-cdk-featureflags.git
Platform: UNKNOWN
Classifier: Intended Audience :: Developers
Classifier: Operating System :: OS Independent
Classifier: Programming Language :: JavaScript
Classifier: Programming Language :: Python :: 3 :: Only
Classifier: Programming Language :: Python :: 3.6
Classifier: Programming Language :: Python :: 3.7
Classifier: Programming Language :: Python :: 3.8
Classifier: Typing :: Typed
Classifier: Development Status :: 4 - Beta
Classifier: License :: OSI Approved
Requires-Python: >=3.6
Requires-Dist: jsii (~=0.22.0)
Requires-Dist: publication (>=0.0.3)
Requires-Dist: aws-cdk.aws-apigateway (<2.0.0,>=1.27.0)
Requires-Dist: aws-cdk.aws-dynamodb (<2.0.0,>=1.27.0)
Requires-Dist: aws-cdk.aws-lambda (<2.0.0,>=1.27.0)
Requires-Dist: aws-cdk.core (<2.0.0,>=1.27.0)
